ingestion/__init__.py
ingestion/broad/__init__.py
ingestion/broad/process.py
ingestion/broad/utils.py
ingestion/caris/__init__.py
ingestion/caris/process.py
ingestion/caris/util/__init__.py
ingestion/caris/util/cnv.py
ingestion/caris/util/detect_genome_ref.py
ingestion/caris/util/hla.py
ingestion/caris/util/ihc.py
ingestion/caris/util/interpretation.py
ingestion/caris/util/json.py
ingestion/caris/util/metadata.py
ingestion/caris/util/specimen_details.py
ingestion/caris/util/structural.py
ingestion/caris/util/tests.py
ingestion/caris/util/tmb.py
ingestion/caris/util/tsv.py
ingestion/caris/util/vcf.py
ingestion/foundation/__init__.py
ingestion/foundation/process.py
ingestion/foundation/util/__init__.py
ingestion/foundation/util/cnv.py
ingestion/foundation/util/fnv.py
ingestion/foundation/util/ga4gh.py
ingestion/foundation/util/interpretation.py
ingestion/foundation/util/vcf_etl.py
ingestion/generic/__init__.py
ingestion/generic/process.py
ingestion/generic/utils.py
ingestion/nebula/__init__.py
ingestion/nebula/constants.py
ingestion/nebula/manifest_assembler.py
ingestion/nebula/process.py
ingestion/nextgen/__init__.py
ingestion/nextgen/process.py
ingestion/nextgen/util/alteration_table.py
ingestion/nextgen/util/interpretation.py
ingestion/nextgen/util/manifest_helpers.py
ingestion/nextgen/util/nextgen_specific_genes.py
ingestion/nextgen/util/pre_filter_somatic_vcf.py
ingestion/nextgen/util/process_cnv.py
ingestion/nextgen/util/process_manifest.py
ingestion/nextgen/util/process_structural.py
ingestion/nextgen/util/process_vcf.py
ingestion/nextgen/util/types.py
ingestion/resources/GRCh37_map.csv.gz
ingestion/resources/GRCh38_map.csv.gz
ingestion/shared_util/__init__.py
ingestion/shared_util/coords_to_genes.py
ingestion/shared_util/fetch_patient.py
ingestion/shared_util/ga4gh.py
ingestion/shared_util/gene_to_coords.py
ingestion/shared_util/lambda_client.py
ingestion/shared_util/open_maybe_gzipped.py
ingestion/shared_util/tar.py
ingestion/shared_util/types.py
phc_ingestion-1.0.3.dist-info/WHEEL
phc_ingestion-1.0.3.dist-info/METADATA
phc_ingestion-1.0.3.dist-info/RECORD
