Metadata-Version: 2.1
Name: phc-ingestion
Version: 1.0.3
Summary: Functions for LifeOmic PHC genomic ingestions
License: MIT
Author-email: LifeOmic Development <development@lifeomic.com>
Requires-Python: >=3.11
Requires-Dist: boto3>=1.28.34
Requires-Dist: jsonschema<5.0.0,>=4.16.0
Requires-Dist: lifeomic-logging<0.4.0,>=0.3.2
Requires-Dist: mypy-boto3-lambda>=1.28.19
Requires-Dist: natsort==7.1.1
Requires-Dist: numpy>=2.1.2
Requires-Dist: packaging>=23.1
Requires-Dist: pandas>=2.2.3
Requires-Dist: ruamel.yaml==0.17.21
Requires-Dist: schema>=0.7.5
Requires-Dist: urllib3>=1.26.16
Requires-Dist: xmltodict>=0.14.2
